lbpackages/__init__.py
lbpackages/constants.py
lbpackages/create_tables/__init__.py
lbpackages/create_tables/create_tables.py
lbpackages/exceptions/__init__.py
lbpackages/exceptions/exceptions.py
lbpackages/get_data/__init__.py
lbpackages/get_data/get_data.py
lbpackages/models/__init__.py
lbpackages/models/dbclient.py
lbpackages/models/stocks.py
lbpackages/plotting/__init__.py
lbpackages/plotting/plotting.py
lbpackages/query_db/__init__.py
lbpackages/query_db/query_db.py
lbpackages/upload_data/__init__.py
lbpackages/upload_data/upload_data.py
lbpackages-0.3.1.dist-info/WHEEL
lbpackages-0.3.1.dist-info/METADATA
lbpackages-0.3.1.dist-info/RECORD
